yaqd_omega/VERSION
yaqd_omega/__init__.py
yaqd_omega/__version__.py
yaqd_omega/_omega_d8200.py
yaqd_omega/_omega_iseries_modbus.py
yaqd_omega/_omega_platinum.py
yaqd_omega/omega-d8200.avpr
yaqd_omega/omega-d8200.toml
yaqd_omega/omega-iseries-modbus.avpr
yaqd_omega/omega-iseries-modbus.toml
yaqd_omega/omega-platinum.avpr
yaqd_omega/omega-platinum.toml
yaqd_omega-2023.11.0.dist-info/entry_points.txt
yaqd_omega-2023.11.0.dist-info/LICENSE
yaqd_omega-2023.11.0.dist-info/WHEEL
yaqd_omega-2023.11.0.dist-info/METADATA
yaqd_omega-2023.11.0.dist-info/RECORD
